pycateda/__init__.py
pycateda-1.0.8.dist-info/LICENSE
pycateda-1.0.8.dist-info/METADATA
pycateda-1.0.8.dist-info/WHEEL
pycateda-1.0.8.dist-info/top_level.txt
pycateda-1.0.8.dist-info/RECORD
