Metadata-Version: 2.1
Name: pycateda
Version: 1.0.8
Summary: pycateda Python Package - A simplified Exploratory Data Analysis with less lines of code
Home-page: https://github.com/arjuns2020/pycateda
Author: Arjun Srinivasa Murthy
Author-email: arjunsm2020@gmail.com
License: MIT
Platform: UNKNOWN
Classifier: Programming Language :: Python :: 3
Classifier: License :: OSI Approved :: MIT License
Classifier: Operating System :: OS Independent
Requires-Python: >=3.5
Requires-Dist: matplotlib
Requires-Dist: numpy
Requires-Dist: pandas
Requires-Dist: seaborn
Requires-Dist: missingno
